datatoolz/__init__.py
datatoolz/filesystem.py
datatoolz/filtering.py
datatoolz/io.py
datatoolz/logging.py
datatoolz/utils.py
data_toolz-0.1.11.dist-info/LICENSE.md
data_toolz-0.1.11.dist-info/METADATA
data_toolz-0.1.11.dist-info/WHEEL
data_toolz-0.1.11.dist-info/top_level.txt
data_toolz-0.1.11.dist-info/RECORD
