Metadata-Version: 2.1
Name: data-toolz
Version: 0.1.11
Summary: Data helper package
Home-page: https://github.com/grzegorzme/data-toolz
Author: Grzegorz Melniczak
Author-email: mogadish@gmail.com
Classifier: Programming Language :: Python :: 3
Requires-Python: >=3.10
License-File: LICENSE.md
Requires-Dist: s3fs ==0.4.2
Requires-Dist: pandas
Requires-Dist: pyarrow
